crms/__init__.py
crms/crms.py
crms/watchdog.py
crms/other_data/m1.pth
crms/other_data/m2.pth
crms-2023.5.3.1340.dist-info/METADATA
crms-2023.5.3.1340.dist-info/WHEEL
crms-2023.5.3.1340.dist-info/entry_points.txt
crms-2023.5.3.1340.dist-info/top_level.txt
crms-2023.5.3.1340.dist-info/RECORD
