Metadata-Version: 2.1
Name: crms
Version: 2023.5.3.1340
Summary: Cloud Robot Model Sharing Middleware
Home-page: https://github.com/jangcs/crms
Author: jangcs
Author-email: jangcs@etri.re.kr
License: UNKNOWN
Platform: UNKNOWN
Requires-Python: >=3.8
Requires-Dist: GitPython (==3.1.27)
Requires-Dist: dvc (==2.15.0)
Requires-Dist: firebase-admin (==5.2.0)
Requires-Dist: fsspec (==2022.2.0)
Requires-Dist: protobuf (==3.20.1)
Requires-Dist: requests (>=2.28.1)
